django_htmx_live_trigger/__init__.py
django_htmx_live_trigger/admin.py
django_htmx_live_trigger/apps.py
django_htmx_live_trigger/consumers.py
django_htmx_live_trigger/models.py
django_htmx_live_trigger/tests.py
django_htmx_live_trigger/static/django_htmx_live_trigger/js/htmx-ws-events.js
django_htmx_live_trigger-0.6.dist-info/LICENSE
django_htmx_live_trigger-0.6.dist-info/METADATA
django_htmx_live_trigger-0.6.dist-info/WHEEL
django_htmx_live_trigger-0.6.dist-info/top_level.txt
django_htmx_live_trigger-0.6.dist-info/RECORD
