Metadata-Version: 2.2
Name: django-htmx-live-trigger
Version: 0.6
Summary: Realtime updates in Django using HTMX and websockets.
Home-page: https://github.com/paulik123
Author: Cornel Kenef
Author-email: paul@2na.dev
License: MIT
Classifier: Environment :: Web Environment
Classifier: Intended Audience :: Developers
Classifier: License :: OSI Approved :: MIT License
Classifier: Operating System :: OS Independent
Classifier: Programming Language :: Python
Classifier: Programming Language :: Python :: 3
Classifier: Programming Language :: Python :: 3 :: Only
Classifier: Programming Language :: Python :: 3.10
Classifier: Programming Language :: Python :: 3.11
Classifier: Programming Language :: Python :: 3.12
Classifier: Framework :: Django
Classifier: Framework :: Django :: 4.2
Classifier: Framework :: Django :: 5.0
Classifier: Topic :: Internet :: WWW/HTTP
Classifier: Topic :: Internet :: WWW/HTTP :: Dynamic Content
Requires-Python: >=3.8
License-File: LICENSE
Requires-Dist: Django>=4.2
Requires-Dist: channels>=4.0
Requires-Dist: daphne>=4.0.0
Requires-Dist: django-redis>=5.0
Requires-Dist: channels-redis>=4.0
